Metadata-Version: 2.1
Name: pyhhmm
Version: 2.0.0
Summary: PyHHMM - Python implementation of HMM with labels
Home-page: https://github.com/fmorenopino/HeterogeneousHMM
Author: Emese Sukei, Fernando Moreno-Pino
Author-email: esukei@tsc.uc3m.es, fmoreno@tsc.uc3m.es
License: UNKNOWN
Platform: UNKNOWN
Classifier: Intended Audience :: Science/Research
Classifier: License :: OSI Approved :: Apache Software License
Classifier: Natural Language :: English
Classifier: Programming Language :: Python
Classifier: Programming Language :: Python :: 3
Classifier: Topic :: Documentation :: Sphinx
Classifier: Topic :: Scientific/Engineering :: Artificial Intelligence
Provides-Extra: test
Provides-Extra: dev
License-File: LICENSE
